birdeye/__init__.py
birdeye/consts.py
birdeye/http_client.py
birdeye/http_client.pyi
birdeye/http_resp.py
birdeye/ratelimiter.py
birdeye/ws_info.py
pybirdeye-0.0.5.dist-info/METADATA
pybirdeye-0.0.5.dist-info/WHEEL
pybirdeye-0.0.5.dist-info/top_level.txt
pybirdeye-0.0.5.dist-info/RECORD
