Metadata-Version: 2.4
Name: pybirdeye
Version: 0.0.5
Home-page: 
Requires-Dist: httpx
Dynamic: description
Dynamic: description-content-type
Dynamic: requires-dist
